htmx_datatables/__init__.py
htmx_datatables/apps.py
htmx_datatables/core.py
htmx_datatables/helpers.py
htmx_datatables/views.py
htmx_datatables/static/htmx_datatables/css/bs3_fix.css
htmx_datatables/static/htmx_datatables/img/Spinner-1s-64px-dark.gif
htmx_datatables/static/htmx_datatables/img/Spinner-1s-64px-light.gif
htmx_datatables/static/htmx_datatables/img/bars-rotate-fade-black-36.svg
htmx_datatables/static/htmx_datatables/img/bars-rotate-fade-white-36.svg
htmx_datatables/static/htmx_datatables/js/vendor/htmx/htmx.min.js
htmx_datatables/templates/htmx_datatables/_data.html
htmx_datatables/templates/htmx_datatables/_filter.html
htmx_datatables/templates/htmx_datatables/_main.html
htmx_datatables/templates/htmx_datatables/_pagination.html
htmx_datatables/templates/htmx_datatables/_spinner.html
htmx_datatables/templates/htmx_datatables/data_table.html
htmx_datatables/templates/htmx_datatables/enable_htmx.html
htmx_datatables/templatetags/__init__.py
htmx_datatables/templatetags/htmx_datatables.py
htmx_datatables/tests/__init__.py
htmx_datatables/tests/test_core.py
htmx_datatables/tests/test_helpers.py
htmx_datatables/tests/test_templatetags.py
htmx_datatables/tests/test_views.py
django_htmx_datatables-0.1.0a1.dist-info/LICENSE
django_htmx_datatables-0.1.0a1.dist-info/WHEEL
django_htmx_datatables-0.1.0a1.dist-info/METADATA
django_htmx_datatables-0.1.0a1.dist-info/RECORD
